pyxir/__init__.py
pyxir-0.0.1.dist-info/METADATA
pyxir-0.0.1.dist-info/WHEEL
pyxir-0.0.1.dist-info/top_level.txt
pyxir-0.0.1.dist-info/RECORD
