Metadata-Version: 2.1
Name: pyxir
Version: 0.0.1
Summary: First version of PyXIR package
Home-page: UNKNOWN
Author: Jorn Tuyls
Author-email: jorn.tuyls@icloud.com
License: UNKNOWN
Platform: UNKNOWN
Classifier: Programming Language :: Python :: 3
Classifier: License :: OSI Approved :: MIT License
Classifier: Operating System :: OS Independent
Requires-Python: >=3.6
